[
{
"asset_id":
"a87e3083-9374-4199-97a6-60f3a769bc34",
"blob":
"b54c2e7d-df50-4891-b501-0764d2adf143",
"created":
"2024-06-14T14:08:27.186794Z",
"metadata":
{
"@context":
"https://raw.githubusercontent.com/dandi/schema/master/releases/0.6.7/context.json",
"access":
[
{
"schemaKey":
"AccessRequirements",
"status":
"dandi:OpenAccess"
}
],
"approach":
[],
"blobDateModified":
"2024-06-14T11:38:06.040650+01:00",
"contentSize":
383881555,
"contentUrl":
[
"https://api.dandiarchive.org/api/assets/a87e3083-9374-4199-97a6-60f3a769bc34/download/",
"https://dandiarchive.s3.amazonaws.com/blobs/b54/c2e/b54c2e7d-df50-4891-b501-0764d2adf143"
],
"dateModified":
"2024-06-14T15:05:22.168194+01:00",
"digest":
{
"dandi:dandi-etag":
"ed795ee4d82a0800d326bcdcf64959e3-6",
"dandi:sha2-256":
"7c4071591f01b7165f700f2721eea4415ef753bb6762bc0ebc986044abef8359"
},
"encodingFormat":
"application/x-nwb",
"id":
"dandiasset:a87e3083-9374-4199-97a6-60f3a769bc34",
"identifier":
"a87e3083-9374-4199-97a6-60f3a769bc34",
"keywords":
[
"benchmark",
"monkey",
"key",
"grasp"
],
"measurementTechnique":
[
{
"name":
"analytical technique",
"schemaKey":
"MeasurementTechniqueType"
}
],
"path":
"sub-0001/sub-0001_ses-1.nwb",
"relatedResource":
[],
"schemaKey":
"Asset",
"schemaVersion":
"0.6.7",
"variableMeasured":
[
{
"schemaKey":
"PropertyValue",
"value":
"ProcessingModule"
}
],
"wasAttributedTo":
[
{
"age":
{
"schemaKey":
"PropertyValue",
"unitText":
"ISO-8601 duration",
"value":
"P10M",
"valueReference":
{
"schemaKey":
"PropertyValue",
"value":
"dandi:BirthReference"
}
},
"identifier":
"0001",
"schemaKey":
"Participant",
"sex":
{
"identifier":
"http://purl.obolibrary.org/obo/PATO_0000384",
"name":
"Male",
"schemaKey":
"SexType"
},
"species":
{
"identifier":
"http://purl.obolibrary.org/obo/NCBITaxon_9544",
"name":
"Macaca mulatta - Rhesus monkey",
"schemaKey":
"SpeciesType"
}
}
],
"wasGeneratedBy":
[
{
"description":
"Key grasp task",
"identifier":
"1",
"name":
"1",
"schemaKey":
"Session",
"startDate":
"2016-08-22T02:30:03-07:00"
},
{
"description":
"Metadata generated by DANDI cli",
"endDate":
"2024-06-14T15:05:22.168180+01:00",
"id":
"urn:uuid:697700b5-f6f4-48a6-be05-2e9881269a19",
"name":
"Metadata generation",
"schemaKey":
"Activity",
"startDate":
"2024-06-14T15:05:22.147769+01:00",
"wasAssociatedWith":
[
{
"identifier":
"RRID:SCR_019009",
"name":
"DANDI Command Line Interface",
"schemaKey":
"Software",
"url":
"https://github.com/dandi/dandi-cli",
"version":
"0.62.1"
}
]
}
]
},
"modified":
"2024-06-14T14:08:27.186808Z",
"path":
"sub-0001/sub-0001_ses-1.nwb",
"size":
383881555
},
{
"asset_id":
"ea660319-368a-4ed6-9c48-14cfd762e95a",
"blob":
"9601abda-ddfe-49af-b39f-fd4f8a75d55f",
"created":
"2024-06-14T14:09:49.185511Z",
"metadata":
{
"@context":
"https://raw.githubusercontent.com/dandi/schema/master/releases/0.6.7/context.json",
"access":
[
{
"schemaKey":
"AccessRequirements",
"status":
"dandi:OpenAccess"
}
],
"approach":
[],
"blobDateModified":
"2024-06-14T11:38:08.090238+01:00",
"contentSize":
830321393,
"contentUrl":
[
"https://api.dandiarchive.org/api/assets/ea660319-368a-4ed6-9c48-14cfd762e95a/download/",
"https://dandiarchive.s3.amazonaws.com/blobs/960/1ab/9601abda-ddfe-49af-b39f-fd4f8a75d55f"
],
"dateModified":
"2024-06-14T15:05:23.431225+01:00",
"digest":
{
"dandi:dandi-etag":
"af07ba612138ae956c9ee01b46e52706-13",
"dandi:sha2-256":
"28de39d7530caa2c3475b9a7d8062df8c43d3871889053a2db4143417a7f2e70"
},
"encodingFormat":
"application/x-nwb",
"id":
"dandiasset:ea660319-368a-4ed6-9c48-14cfd762e95a",
"identifier":
"ea660319-368a-4ed6-9c48-14cfd762e95a",
"keywords":
[
"benchmark",
"monkey",
"key",
"grasp"
],
"measurementTechnique":
[
{
"name":
"analytical technique",
"schemaKey":
"MeasurementTechniqueType"
}
],
"path":
"sub-0001/sub-0001_ses-2.nwb",
"relatedResource":
[],
"schemaKey":
"Asset",
"schemaVersion":
"0.6.7",
"variableMeasured":
[
{
"schemaKey":
"PropertyValue",
"value":
"ProcessingModule"
}
],
"wasAttributedTo":
[
{
"age":
{
"schemaKey":
"PropertyValue",
"unitText":
"ISO-8601 duration",
"value":
"P10M",
"valueReference":
{
"schemaKey":
"PropertyValue",
"value":
"dandi:BirthReference"
}
},
"identifier":
"0001",
"schemaKey":
"Participant",
"sex":
{
"identifier":
"http://purl.obolibrary.org/obo/PATO_0000384",
"name":
"Male",
"schemaKey":
"SexType"
},
"species":
{
"identifier":
"http://purl.obolibrary.org/obo/NCBITaxon_9544",
"name":
"Macaca mulatta - Rhesus monkey",
"schemaKey":
"SpeciesType"
}
}
],
"wasGeneratedBy":
[
{
"description":
"Key grasp task",
"identifier":
"2",
"name":
"2",
"schemaKey":
"Session",
"startDate":
"2016-08-22T02:30:03-07:00"
},
{
"description":
"Metadata generated by DANDI cli",
"endDate":
"2024-06-14T15:05:23.431210+01:00",
"id":
"urn:uuid:be16a88e-303d-407b-8637-90276caa8a55",
"name":
"Metadata generation",
"schemaKey":
"Activity",
"startDate":
"2024-06-14T15:05:23.428911+01:00",
"wasAssociatedWith":
[
{
"identifier":
"RRID:SCR_019009",
"name":
"DANDI Command Line Interface",
"schemaKey":
"Software",
"url":
"https://github.com/dandi/dandi-cli",
"version":
"0.62.1"
}
]
}
]
},
"modified":
"2024-06-14T14:09:49.185529Z",
"path":
"sub-0001/sub-0001_ses-2.nwb",
"size":
830321393
},
{
"asset_id":
"be8cd7a9-5f19-40ab-b672-2cee7bb6a909",
"blob":
"e5c96753-c5be-422f-a253-84431fcb0462",
"created":
"2024-06-14T14:08:00.553356Z",
"metadata":
{
"@context":
"https://raw.githubusercontent.com/dandi/schema/master/releases/0.6.7/context.json",
"access":
[
{
"schemaKey":
"AccessRequirements",
"status":
"dandi:OpenAccess"
}
],
"approach":
[],
"blobDateModified":
"2024-06-14T11:38:09.262073+01:00",
"contentSize":
354579807,
"contentUrl":
[
"https://api.dandiarchive.org/api/assets/be8cd7a9-5f19-40ab-b672-2cee7bb6a909/download/",
"https://dandiarchive.s3.amazonaws.com/blobs/e5c/967/e5c96753-c5be-422f-a253-84431fcb0462"
],
"dateModified":
"2024-06-14T15:05:22.299091+01:00",
"digest":
{
"dandi:dandi-etag":
"75f70b6d897213b05c4ba475437c07de-6",
"dandi:sha2-256":
"7600b1ad0a8e3d8c369342e599c49698579f2b7cca15528b9208b5e09465934c"
},
"encodingFormat":
"application/x-nwb",
"id":
"dandiasset:be8cd7a9-5f19-40ab-b672-2cee7bb6a909",
"identifier":
"be8cd7a9-5f19-40ab-b672-2cee7bb6a909",
"keywords":
[
"benchmark",
"monkey",
"key",
"grasp"
],
"measurementTechnique":
[
{
"name":
"analytical technique",
"schemaKey":
"MeasurementTechniqueType"
}
],
"path":
"sub-0001/sub-0001_ses-3.nwb",
"relatedResource":
[],
"schemaKey":
"Asset",
"schemaVersion":
"0.6.7",
"variableMeasured":
[
{
"schemaKey":
"PropertyValue",
"value":
"ProcessingModule"
}
],
"wasAttributedTo":
[
{
"age":
{
"schemaKey":
"PropertyValue",
"unitText":
"ISO-8601 duration",
"value":
"P10M",
"valueReference":
{
"schemaKey":
"PropertyValue",
"value":
"dandi:BirthReference"
}
},
"identifier":
"0001",
"schemaKey":
"Participant",
"sex":
{
"identifier":
"http://purl.obolibrary.org/obo/PATO_0000384",
"name":
"Male",
"schemaKey":
"SexType"
},
"species":
{
"identifier":
"http://purl.obolibrary.org/obo/NCBITaxon_9544",
"name":
"Macaca mulatta - Rhesus monkey",
"schemaKey":
"SpeciesType"
}
}
],
"wasGeneratedBy":
[
{
"description":
"Key grasp task",
"identifier":
"3",
"name":
"3",
"schemaKey":
"Session",
"startDate":
"2016-08-22T02:30:03-07:00"
},
{
"description":
"Metadata generated by DANDI cli",
"endDate":
"2024-06-14T15:05:22.299079+01:00",
"id":
"urn:uuid:7af6b8e8-5470-4b67-9a75-6af19c1de9d3",
"name":
"Metadata generation",
"schemaKey":
"Activity",
"startDate":
"2024-06-14T15:05:22.284229+01:00",
"wasAssociatedWith":
[
{
"identifier":
"RRID:SCR_019009",
"name":
"DANDI Command Line Interface",
"schemaKey":
"Software",
"url":
"https://github.com/dandi/dandi-cli",
"version":
"0.62.1"
}
]
}
]
},
"modified":
"2024-06-14T14:08:00.553386Z",
"path":
"sub-0001/sub-0001_ses-3.nwb",
"size":
354579807
},
{
"asset_id":
"656f54b9-32d3-4de8-a09d-450ec76af843",
"blob":
"0ac78e00-c4d5-4475-8618-dd586a90c7c9",
"created":
"2024-06-14T14:07:54.854359Z",
"metadata":
{
"@context":
"https://raw.githubusercontent.com/dandi/schema/master/releases/0.6.7/context.json",
"access":
[
{
"schemaKey":
"AccessRequirements",
"status":
"dandi:OpenAccess"
}
],
"approach":
[],
"blobDateModified":
"2024-06-14T11:38:10.259388+01:00",
"contentSize":
305418156,
"contentUrl":
[
"https://api.dandiarchive.org/api/assets/656f54b9-32d3-4de8-a09d-450ec76af843/download/",
"https://dandiarchive.s3.amazonaws.com/blobs/0ac/78e/0ac78e00-c4d5-4475-8618-dd586a90c7c9"
],
"dateModified":
"2024-06-14T15:05:22.175300+01:00",
"digest":
{
"dandi:dandi-etag":
"47b4e1d61e5826baa07ce41b09dde50d-5",
"dandi:sha2-256":
"143500944763fcacf4baae19c72572b38dc5fac5c726991922b01ad5b63c8381"
},
"encodingFormat":
"application/x-nwb",
"id":
"dandiasset:656f54b9-32d3-4de8-a09d-450ec76af843",
"identifier":
"656f54b9-32d3-4de8-a09d-450ec76af843",
"keywords":
[
"benchmark",
"monkey",
"key",
"grasp"
],
"measurementTechnique":
[
{
"name":
"analytical technique",
"schemaKey":
"MeasurementTechniqueType"
}
],
"path":
"sub-0001/sub-0001_ses-4.nwb",
"relatedResource":
[],
"schemaKey":
"Asset",
"schemaVersion":
"0.6.7",
"variableMeasured":
[
{
"schemaKey":
"PropertyValue",
"value":
"ProcessingModule"
}
],
"wasAttributedTo":
[
{
"age":
{
"schemaKey":
"PropertyValue",
"unitText":
"ISO-8601 duration",
"value":
"P10M",
"valueReference":
{
"schemaKey":
"PropertyValue",
"value":
"dandi:BirthReference"
}
},
"identifier":
"0001",
"schemaKey":
"Participant",
"sex":
{
"identifier":
"http://purl.obolibrary.org/obo/PATO_0000384",
"name":
"Male",
"schemaKey":
"SexType"
},
"species":
{
"identifier":
"http://purl.obolibrary.org/obo/NCBITaxon_9544",
"name":
"Macaca mulatta - Rhesus monkey",
"schemaKey":
"SpeciesType"
}
}
],
"wasGeneratedBy":
[
{
"description":
"Key grasp task",
"identifier":
"4",
"name":
"4",
"schemaKey":
"Session",
"startDate":
"2016-08-22T02:30:03-07:00"
},
{
"description":
"Metadata generated by DANDI cli",
"endDate":
"2024-06-14T15:05:22.175275+01:00",
"id":
"urn:uuid:bd3724af-ae76-460f-9586-53fb1ec96614",
"name":
"Metadata generation",
"schemaKey":
"Activity",
"startDate":
"2024-06-14T15:05:22.167173+01:00",
"wasAssociatedWith":
[
{
"identifier":
"RRID:SCR_019009",
"name":
"DANDI Command Line Interface",
"schemaKey":
"Software",
"url":
"https://github.com/dandi/dandi-cli",
"version":
"0.62.1"
}
]
}
]
},
"modified":
"2024-06-14T14:07:54.854373Z",
"path":
"sub-0001/sub-0001_ses-4.nwb",
"size":
305418156
},
{
"asset_id":
"8890068d-6eef-4252-9157-b193b7aad5a9",
"blob":
"de8d0092-9bea-49ce-9e77-409217a135fb",
"created":
"2024-06-14T14:07:41.927551Z",
"metadata":
{
"@context":
"https://raw.githubusercontent.com/dandi/schema/master/releases/0.6.7/context.json",
"access":
[
{
"schemaKey":
"AccessRequirements",
"status":
"dandi:OpenAccess"
}
],
"approach":
[],
"blobDateModified":
"2024-06-14T11:38:11.069600+01:00",
"contentSize":
237631173,
"contentUrl":
[
"https://api.dandiarchive.org/api/assets/8890068d-6eef-4252-9157-b193b7aad5a9/download/",
"https://dandiarchive.s3.amazonaws.com/blobs/de8/d00/de8d0092-9bea-49ce-9e77-409217a135fb"
],
"dateModified":
"2024-06-14T15:05:21.709789+01:00",
"digest":
{
"dandi:dandi-etag":
"7e3085524cf7f19a3730413619f52e33-4",
"dandi:sha2-256":
"561c097eca7d5802fbf4e0d30029008fbf9ec0b06750acaf3ed7b282fc0e5439"
},
"encodingFormat":
"application/x-nwb",
"id":
"dandiasset:8890068d-6eef-4252-9157-b193b7aad5a9",
"identifier":
"8890068d-6eef-4252-9157-b193b7aad5a9",
"keywords":
[
"benchmark",
"monkey",
"key",
"grasp"
],
"measurementTechnique":
[
{
"name":
"analytical technique",
"schemaKey":
"MeasurementTechniqueType"
}
],
"path":
"sub-0001/sub-0001_ses-5.nwb",
"relatedResource":
[],
"schemaKey":
"Asset",
"schemaVersion":
"0.6.7",
"variableMeasured":
[
{
"schemaKey":
"PropertyValue",
"value":
"ProcessingModule"
}
],
"wasAttributedTo":
[
{
"age":
{
"schemaKey":
"PropertyValue",
"unitText":
"ISO-8601 duration",
"value":
"P10M",
"valueReference":
{
"schemaKey":
"PropertyValue",
"value":
"dandi:BirthReference"
}
},
"identifier":
"0001",
"schemaKey":
"Participant",
"sex":
{
"identifier":
"http://purl.obolibrary.org/obo/PATO_0000384",
"name":
"Male",
"schemaKey":
"SexType"
},
"species":
{
"identifier":
"http://purl.obolibrary.org/obo/NCBITaxon_9544",
"name":
"Macaca mulatta - Rhesus monkey",
"schemaKey":
"SpeciesType"
}
}
],
"wasGeneratedBy":
[
{
"description":
"Key grasp task",
"identifier":
"5",
"name":
"5",
"schemaKey":
"Session",
"startDate":
"2016-08-22T02:30:03-07:00"
},
{
"description":
"Metadata generated by DANDI cli",
"endDate":
"2024-06-14T15:05:21.709772+01:00",
"id":
"urn:uuid:9fac6205-2404-423d-8148-5010fdf69be9",
"name":
"Metadata generation",
"schemaKey":
"Activity",
"startDate":
"2024-06-14T15:05:21.683767+01:00",
"wasAssociatedWith":
[
{
"identifier":
"RRID:SCR_019009",
"name":
"DANDI Command Line Interface",
"schemaKey":
"Software",
"url":
"https://github.com/dandi/dandi-cli",
"version":
"0.62.1"
}
]
}
]
},
"modified":
"2024-06-14T14:07:41.927568Z",
"path":
"sub-0001/sub-0001_ses-5.nwb",
"size":
237631173
},
{
"asset_id":
"460a455a-e88b-4f04-9122-538331d783e0",
"blob":
"1d2c37bd-7404-428b-8029-36ca0677477c",
"created":
"2024-06-14T14:09:38.569722Z",
"metadata":
{
"@context":
"https://raw.githubusercontent.com/dandi/schema/master/releases/0.6.7/context.json",
"access":
[
{
"schemaKey":
"AccessRequirements",
"status":
"dandi:OpenAccess"
}
],
"approach":
[],
"blobDateModified":
"2024-06-14T11:38:12.108520+01:00",
"contentSize":
263878907,
"contentUrl":
[
"https://api.dandiarchive.org/api/assets/460a455a-e88b-4f04-9122-538331d783e0/download/",
"https://dandiarchive.s3.amazonaws.com/blobs/1d2/c37/1d2c37bd-7404-428b-8029-36ca0677477c"
],
"dateModified":
"2024-06-14T15:07:42.921944+01:00",
"digest":
{
"dandi:dandi-etag":
"095139a8ff9f23b0e925a7f3450253d8-4",
"dandi:sha2-256":
"1d90566b26b0114ba3ff1a2347b4017dbb65d3d496f3cea69fbbf672107552d9"
},
"encodingFormat":
"application/x-nwb",
"id":
"dandiasset:460a455a-e88b-4f04-9122-538331d783e0",
"identifier":
"460a455a-e88b-4f04-9122-538331d783e0",
"keywords":
[
"benchmark",
"monkey",
"key",
"grasp"
],
"measurementTechnique":
[
{
"name":
"analytical technique",
"schemaKey":
"MeasurementTechniqueType"
}
],
"path":
"sub-0001/sub-0001_ses-6.nwb",
"relatedResource":
[],
"schemaKey":
"Asset",
"schemaVersion":
"0.6.7",
"variableMeasured":
[
{
"schemaKey":
"PropertyValue",
"value":
"ProcessingModule"
}
],
"wasAttributedTo":
[
{
"age":
{
"schemaKey":
"PropertyValue",
"unitText":
"ISO-8601 duration",
"value":
"P10M",
"valueReference":
{
"schemaKey":
"PropertyValue",
"value":
"dandi:BirthReference"
}
},
"identifier":
"0001",
"schemaKey":
"Participant",
"sex":
{
"identifier":
"http://purl.obolibrary.org/obo/PATO_0000384",
"name":
"Male",
"schemaKey":
"SexType"
},
"species":
{
"identifier":
"http://purl.obolibrary.org/obo/NCBITaxon_9544",
"name":
"Macaca mulatta - Rhesus monkey",
"schemaKey":
"SpeciesType"
}
}
],
"wasGeneratedBy":
[
{
"description":
"Key grasp task",
"identifier":
"6",
"name":
"6",
"schemaKey":
"Session",
"startDate":
"2016-08-22T02:30:03-07:00"
},
{
"description":
"Metadata generated by DANDI cli",
"endDate":
"2024-06-14T15:07:42.921931+01:00",
"id":
"urn:uuid:2282fcf9-7176-4e7f-aa3a-8dcd85571ede",
"name":
"Metadata generation",
"schemaKey":
"Activity",
"startDate":
"2024-06-14T15:07:42.919704+01:00",
"wasAssociatedWith":
[
{
"identifier":
"RRID:SCR_019009",
"name":
"DANDI Command Line Interface",
"schemaKey":
"Software",
"url":
"https://github.com/dandi/dandi-cli",
"version":
"0.62.1"
}
]
}
]
},
"modified":
"2024-06-14T14:09:38.569744Z",
"path":
"sub-0001/sub-0001_ses-6.nwb",
"size":
263878907
},
{
"asset_id":
"579ed6b2-0aa9-43e5-812a-49f5530f1acf",
"blob":
"f7d31d3d-61e1-4315-9bde-1e29b5ae7039",
"created":
"2024-06-14T14:09:48.763248Z",
"metadata":
{
"@context":
"https://raw.githubusercontent.com/dandi/schema/master/releases/0.6.7/context.json",
"access":
[
{
"schemaKey":
"AccessRequirements",
"status":
"dandi:OpenAccess"
}
],
"approach":
[],
"blobDateModified":
"2024-06-14T11:38:13.132919+01:00",
"contentSize":
275560889,
"contentUrl":
[
"https://api.dandiarchive.org/api/assets/579ed6b2-0aa9-43e5-812a-49f5530f1acf/download/",
"https://dandiarchive.s3.amazonaws.com/blobs/f7d/31d/f7d31d3d-61e1-4315-9bde-1e29b5ae7039"
],
"dateModified":
"2024-06-14T15:07:55.904809+01:00",
"digest":
{
"dandi:dandi-etag":
"38d379171d528f8a39d53a4b68f220d5-5",
"dandi:sha2-256":
"f433b2d17748b2a5f93ce17e98281d474920212b7b1408ec0104b9cca8067d48"
},
"encodingFormat":
"application/x-nwb",
"id":
"dandiasset:579ed6b2-0aa9-43e5-812a-49f5530f1acf",
"identifier":
"579ed6b2-0aa9-43e5-812a-49f5530f1acf",
"keywords":
[
"benchmark",
"monkey",
"key",
"grasp"
],
"measurementTechnique":
[
{
"name":
"analytical technique",
"schemaKey":
"MeasurementTechniqueType"
}
],
"path":
"sub-0001/sub-0001_ses-7.nwb",
"relatedResource":
[],
"schemaKey":
"Asset",
"schemaVersion":
"0.6.7",
"variableMeasured":
[
{
"schemaKey":
"PropertyValue",
"value":
"ProcessingModule"
}
],
"wasAttributedTo":
[
{
"age":
{
"schemaKey":
"PropertyValue",
"unitText":
"ISO-8601 duration",
"value":
"P10M",
"valueReference":
{
"schemaKey":
"PropertyValue",
"value":
"dandi:BirthReference"
}
},
"identifier":
"0001",
"schemaKey":
"Participant",
"sex":
{
"identifier":
"http://purl.obolibrary.org/obo/PATO_0000384",
"name":
"Male",
"schemaKey":
"SexType"
},
"species":
{
"identifier":
"http://purl.obolibrary.org/obo/NCBITaxon_9544",
"name":
"Macaca mulatta - Rhesus monkey",
"schemaKey":
"SpeciesType"
}
}
],
"wasGeneratedBy":
[
{
"description":
"Key grasp task",
"identifier":
"7",
"name":
"7",
"schemaKey":
"Session",
"startDate":
"2016-08-22T02:30:03-07:00"
},
{
"description":
"Metadata generated by DANDI cli",
"endDate":
"2024-06-14T15:07:55.904793+01:00",
"id":
"urn:uuid:b02b89c7-00fa-4e45-b33e-bc63f04c6471",
"name":
"Metadata generation",
"schemaKey":
"Activity",
"startDate":
"2024-06-14T15:07:55.902508+01:00",
"wasAssociatedWith":
[
{
"identifier":
"RRID:SCR_019009",
"name":
"DANDI Command Line Interface",
"schemaKey":
"Software",
"url":
"https://github.com/dandi/dandi-cli",
"version":
"0.62.1"
}
]
}
]
},
"modified":
"2024-06-14T14:09:48.763265Z",
"path":
"sub-0001/sub-0001_ses-7.nwb",
"size":
275560889
},
{
"asset_id":
"2c0ca998-361f-47a8-a5ac-4899a09960eb",
"blob":
"154e0a21-79fd-481d-bc37-5c2754ed45bc",
"created":
"2024-06-14T14:10:05.159567Z",
"metadata":
{
"@context":
"https://raw.githubusercontent.com/dandi/schema/master/releases/0.6.7/context.json",
"access":
[
{
"schemaKey":
"AccessRequirements",
"status":
"dandi:OpenAccess"
}
],
"approach":
[],
"blobDateModified":
"2024-06-14T11:38:14.418469+01:00",
"contentSize":
411766200,
"contentUrl":
[
"https://api.dandiarchive.org/api/assets/2c0ca998-361f-47a8-a5ac-4899a09960eb/download/",
"https://dandiarchive.s3.amazonaws.com/blobs/154/e0a/154e0a21-79fd-481d-bc37-5c2754ed45bc"
],
"dateModified":
"2024-06-14T15:08:02.070146+01:00",
"digest":
{
"dandi:dandi-etag":
"e29d56fe0f1df09c0e5f2d05f7ad7995-7",
"dandi:sha2-256":
"210854ec24b75c4af6583a864bfc1bbf2cc2da704f81bb6bf11833b595b08391"
},
"encodingFormat":
"application/x-nwb",
"id":
"dandiasset:2c0ca998-361f-47a8-a5ac-4899a09960eb",
"identifier":
"2c0ca998-361f-47a8-a5ac-4899a09960eb",
"keywords":
[
"benchmark",
"monkey",
"key",
"grasp"
],
"measurementTechnique":
[
{
"name":
"analytical technique",
"schemaKey":
"MeasurementTechniqueType"
}
],
"path":
"sub-0001/sub-0001_ses-8.nwb",
"relatedResource":
[],
"schemaKey":
"Asset",
"schemaVersion":
"0.6.7",
"variableMeasured":
[
{
"schemaKey":
"PropertyValue",
"value":
"ProcessingModule"
}
],
"wasAttributedTo":
[
{
"age":
{
"schemaKey":
"PropertyValue",
"unitText":
"ISO-8601 duration",
"value":
"P10M",
"valueReference":
{
"schemaKey":
"PropertyValue",
"value":
"dandi:BirthReference"
}
},
"identifier":
"0001",
"schemaKey":
"Participant",
"sex":
{
"identifier":
"http://purl.obolibrary.org/obo/PATO_0000384",
"name":
"Male",
"schemaKey":
"SexType"
},
"species":
{
"identifier":
"http://purl.obolibrary.org/obo/NCBITaxon_9544",
"name":
"Macaca mulatta - Rhesus monkey",
"schemaKey":
"SpeciesType"
}
}
],
"wasGeneratedBy":
[
{
"description":
"Key grasp task",
"identifier":
"8",
"name":
"8",
"schemaKey":
"Session",
"startDate":
"2016-08-22T02:30:03-07:00"
},
{
"description":
"Metadata generated by DANDI cli",
"endDate":
"2024-06-14T15:08:02.070131+01:00",
"id":
"urn:uuid:b3537c98-5c12-45c7-ba8f-d206b6a7bd90",
"name":
"Metadata generation",
"schemaKey":
"Activity",
"startDate":
"2024-06-14T15:08:02.068028+01:00",
"wasAssociatedWith":
[
{
"identifier":
"RRID:SCR_019009",
"name":
"DANDI Command Line Interface",
"schemaKey":
"Software",
"url":
"https://github.com/dandi/dandi-cli",
"version":
"0.62.1"
}
]
}
]
},
"modified":
"2024-06-14T14:10:05.159584Z",
"path":
"sub-0001/sub-0001_ses-8.nwb",
"size":
411766200
},
{
"asset_id":
"abc75099-38d3-4a23-9e79-3eab15135627",
"blob":
"ea212354-1eef-4982-9e62-b6368a101113",
"created":
"2024-06-14T14:10:01.386961Z",
"metadata":
{
"@context":
"https://raw.githubusercontent.com/dandi/schema/master/releases/0.6.7/context.json",
"access":
[
{
"schemaKey":
"AccessRequirements",
"status":
"dandi:OpenAccess"
}
],
"approach":
[],
"blobDateModified":
"2024-06-14T11:38:15.353336+01:00",
"contentSize":
297747688,
"contentUrl":
[
"https://api.dandiarchive.org/api/assets/abc75099-38d3-4a23-9e79-3eab15135627/download/",
"https://dandiarchive.s3.amazonaws.com/blobs/ea2/123/ea212354-1eef-4982-9e62-b6368a101113"
],
"dateModified":
"2024-06-14T15:08:28.310590+01:00",
"digest":
{
"dandi:dandi-etag":
"883ff8a892305b654af1e205fdcc2fd9-5",
"dandi:sha2-256":
"1ce941f55e9c230ab08c942c277883c47cc484f662378f3d59e913bec25392ae"
},
"encodingFormat":
"application/x-nwb",
"id":
"dandiasset:abc75099-38d3-4a23-9e79-3eab15135627",
"identifier":
"abc75099-38d3-4a23-9e79-3eab15135627",
"keywords":
[
"benchmark",
"monkey",
"key",
"grasp"
],
"measurementTechnique":
[
{
"name":
"analytical technique",
"schemaKey":
"MeasurementTechniqueType"
}
],
"path":
"sub-0001/sub-0001_ses-9.nwb",
"relatedResource":
[],
"schemaKey":
"Asset",
"schemaVersion":
"0.6.7",
"variableMeasured":
[
{
"schemaKey":
"PropertyValue",
"value":
"ProcessingModule"
}
],
"wasAttributedTo":
[
{
"age":
{
"schemaKey":
"PropertyValue",
"unitText":
"ISO-8601 duration",
"value":
"P10M",
"valueReference":
{
"schemaKey":
"PropertyValue",
"value":
"dandi:BirthReference"
}
},
"identifier":
"0001",
"schemaKey":
"Participant",
"sex":
{
"identifier":
"http://purl.obolibrary.org/obo/PATO_0000384",
"name":
"Male",
"schemaKey":
"SexType"
},
"species":
{
"identifier":
"http://purl.obolibrary.org/obo/NCBITaxon_9544",
"name":
"Macaca mulatta - Rhesus monkey",
"schemaKey":
"SpeciesType"
}
}
],
"wasGeneratedBy":
[
{
"description":
"Key grasp task",
"identifier":
"9",
"name":
"9",
"schemaKey":
"Session",
"startDate":
"2016-08-22T02:30:03-07:00"
},
{
"description":
"Metadata generated by DANDI cli",
"endDate":
"2024-06-14T15:08:28.310578+01:00",
"id":
"urn:uuid:67617fda-6e90-43a1-bb1e-6f95f22316ae",
"name":
"Metadata generation",
"schemaKey":
"Activity",
"startDate":
"2024-06-14T15:08:28.308875+01:00",
"wasAssociatedWith":
[
{
"identifier":
"RRID:SCR_019009",
"name":
"DANDI Command Line Interface",
"schemaKey":
"Software",
"url":
"https://github.com/dandi/dandi-cli",
"version":
"0.62.1"
}
]
}
]
},
"modified":
"2024-06-14T14:10:01.386976Z",
"path":
"sub-0001/sub-0001_ses-9.nwb",
"size":
297747688
}
]